enjarify/__init__.py
enjarify/_version.py
enjarify/byteio.py
enjarify/dalvik.py
enjarify/dalvikformats.py
enjarify/flags.py
enjarify/hashtests.py
enjarify/main.py
enjarify/mutf8.py
enjarify/parsedex.py
enjarify/runtests.py
enjarify/treelist.py
enjarify/util.py
enjarify/jvm/__init__.py
enjarify/jvm/arraytypes.py
enjarify/jvm/constantpool.py
enjarify/jvm/error.py
enjarify/jvm/genmathops.py
enjarify/jvm/ir.py
enjarify/jvm/jvmops.py
enjarify/jvm/mathops.py
enjarify/jvm/scalartypes.py
enjarify/jvm/writebytecode.py
enjarify/jvm/writeclass.py
enjarify/jvm/writeir.py
enjarify/jvm/constants/__init__.py
enjarify/jvm/constants/calc.py
enjarify/jvm/constants/genlookup.py
enjarify/jvm/constants/lookup.py
enjarify/jvm/optimization/__init__.py
enjarify/jvm/optimization/consts.py
enjarify/jvm/optimization/jumps.py
enjarify/jvm/optimization/options.py
enjarify/jvm/optimization/registers.py
enjarify/jvm/optimization/stack.py
enjarify/typeinference/__init__.py
enjarify/typeinference/typeinference.py
enjarify_adapter-1.0.2.dist-info/LICENSE.txt
enjarify_adapter-1.0.2.dist-info/METADATA
enjarify_adapter-1.0.2.dist-info/NOTICE
enjarify_adapter-1.0.2.dist-info/WHEEL
enjarify_adapter-1.0.2.dist-info/entry_points.txt
enjarify_adapter-1.0.2.dist-info/top_level.txt
enjarify_adapter-1.0.2.dist-info/RECORD
