Metadata-Version: 2.1
Name: enjarify-adapter
Version: 1.0.2
Summary: Enjarify is a tool for translating Dalvik bytecode to equivalent Java bytecode. This enjarify-adapter fork exports the `enjarify` method for use in external scripts and is type optimized for building with mypyc.
Home-page: https://github.com/LucasFaudman/enjarify-adapter.git
Author: Lucas Faudman
Author-email: Lucas Faudman <lucasfaudman@gmail.com>, "Google Inc. 2015" <google@gmail.com>, Robert Grosse <Storyyeller@github.com>
License: 
Project-URL: Homepage, https://github.com/LucasFaudman/enjarify-adapter.git
Project-URL: Repository, https://github.com/LucasFaudman/enjarify-adapter.git
Keywords: enjarify,Dalvik,Java,Bytecode,Android,APK,Decompiler,Disassembler,Reverse Engineering
Classifier: Development Status :: 5 - Production/Stable
Classifier: Intended Audience :: Developers
Classifier: License :: OSI Approved :: Apache Software License
Classifier: Programming Language :: Python :: 3
Classifier: Programming Language :: Python :: 3.7
Classifier: Programming Language :: Python :: 3.8
Classifier: Programming Language :: Python :: 3.9
Classifier: Programming Language :: Python :: 3.10
Classifier: Programming Language :: Python :: 3.11
Classifier: Operating System :: OS Independent
Classifier: Topic :: Software Development :: Libraries
Classifier: Topic :: Software Development :: Libraries :: Python Modules
Requires-Python: >=3.7
License-File: LICENSE.txt
License-File: NOTICE
